{
  "annotations": {
    "list": [
      {
        "builtIn": 1,
        "datasource": {
          "type": "grafana",
          "uid": "-- Grafana --"
        },
        "enable": true,
        "hide": true,
        "iconColor": "rgba(0, 211, 255, 1)",
        "name": "Annotations & Alerts",
        "type": "dashboard"
      }
    ]
  },
  "editable": true,
  "fiscalYearStartMonth": 0,
  "graphTooltip": 0,
  "id": 35,
  "links": [],
  "panels": [
    {
      "datasource": {
        "type": "prometheus",
        "uid": "prometheus"
      },
      "fieldConfig": {
        "defaults": {
          "color": {
            "mode": "thresholds"
          },
          "mappings": [],
          "thresholds": {
            "mode": "absolute",
            "steps": [
              {
                "color": "green",
                "value": null
              },
              {
                "color": "red",
                "value": 80
              }
            ]
          }
        },
        "overrides": []
      },
      "gridPos": {
        "h": 8,
        "w": 12,
        "x": 0,
        "y": 0
      },
      "id": 4,
      "options": {
        "colorMode": "value",
        "graphMode": "area",
        "justifyMode": "auto",
        "orientation": "auto",
        "percentChangeColorMode": "standard",
        "reduceOptions": {
          "calcs": [
            "lastNotNull"
          ],
          "fields": "/^version$/",
          "values": false
        },
        "showPercentChange": false,
        "textMode": "auto",
        "wideLayout": true
      },
      "pluginVersion": "11.3.1",
      "targets": [
        {
          "editorMode": "code",
          "expr": "nodejs_version_info{app=\"captcha-api\"}",
          "format": "table",
          "legendFormat": "__auto",
          "range": true,
          "refId": "A"
        }
      ],
      "title": "NodeJS Version",
      "type": "stat"
    },
    {
      "datasource": {
        "type": "prometheus",
        "uid": "prometheus"
      },
      "fieldConfig": {
        "defaults": {
          "color": {
            "mode": "palette-classic"
          },
          "custom": {
            "axisBorderShow": false,
            "axisCenteredZero": false,
            "axisColorMode": "text",
            "axisLabel": "",
            "axisPlacement": "auto",
            "barAlignment": 0,
            "barWidthFactor": 0.6,
            "drawStyle": "line",
            "fillOpacity": 0,
            "gradientMode": "none",
            "hideFrom": {
              "legend": false,
              "tooltip": false,
              "viz": false
            },
            "insertNulls": false,
            "lineInterpolation": "linear",
            "lineWidth": 1,
            "pointSize": 5,
            "scaleDistribution": {
              "type": "linear"
            },
            "showPoints": "auto",
            "spanNulls": false,
            "stacking": {
              "group": "A",
              "mode": "none"
            },
            "thresholdsStyle": {
              "mode": "off"
            }
          },
          "mappings": [],
          "thresholds": {
            "mode": "absolute",
            "steps": [
              {
                "color": "green",
                "value": null
              },
              {
                "color": "red",
                "value": 80
              }
            ]
          },
          "unit": "bytes"
        },
        "overrides": [
          {
            "matcher": {
              "id": "byName",
              "options": "Value #A"
            },
            "properties": [
              {
                "id": "displayName",
                "value": "Resident Memory"
              }
            ]
          },
          {
            "matcher": {
              "id": "byName",
              "options": "Value #B"
            },
            "properties": [
              {
                "id": "displayName",
                "value": "Virtual Memory"
              }
            ]
          },
          {
            "matcher": {
              "id": "byName",
              "options": "Value #C"
            },
            "properties": [
              {
                "id": "displayName",
                "value": "Heap Memory"
              }
            ]
          }
        ]
      },
      "gridPos": {
        "h": 8,
        "w": 12,
        "x": 12,
        "y": 0
      },
      "id": 2,
      "options": {
        "legend": {
          "calcs": [],
          "displayMode": "list",
          "placement": "bottom",
          "showLegend": true
        },
        "tooltip": {
          "mode": "single",
          "sort": "none"
        }
      },
      "pluginVersion": "11.3.1",
      "targets": [
        {
          "editorMode": "code",
          "expr": "process_resident_memory_bytes{app=\"captcha-api\"}",
          "format": "table",
          "legendFormat": "__auto",
          "range": true,
          "refId": "A"
        },
        {
          "datasource": {
            "type": "prometheus",
            "uid": "prometheus"
          },
          "editorMode": "code",
          "expr": "process_virtual_memory_bytes{app=\"captcha-api\"}",
          "format": "table",
          "hide": false,
          "instant": false,
          "legendFormat": "__auto",
          "range": true,
          "refId": "B"
        },
        {
          "datasource": {
            "type": "prometheus",
            "uid": "prometheus"
          },
          "editorMode": "code",
          "expr": "process_heap_bytes{app=\"captcha-api\"}",
          "format": "table",
          "hide": false,
          "instant": false,
          "legendFormat": "__auto",
          "range": true,
          "refId": "C"
        }
      ],
      "title": "Memory Utilization",
      "type": "timeseries"
    },
    {
      "datasource": {
        "type": "prometheus",
        "uid": "prometheus"
      },
      "fieldConfig": {
        "defaults": {
          "color": {
            "mode": "palette-classic"
          },
          "custom": {
            "axisBorderShow": false,
            "axisCenteredZero": false,
            "axisColorMode": "text",
            "axisLabel": "",
            "axisPlacement": "auto",
            "barAlignment": 0,
            "barWidthFactor": 0.6,
            "drawStyle": "line",
            "fillOpacity": 0,
            "gradientMode": "none",
            "hideFrom": {
              "legend": false,
              "tooltip": false,
              "viz": false
            },
            "insertNulls": false,
            "lineInterpolation": "linear",
            "lineWidth": 1,
            "pointSize": 5,
            "scaleDistribution": {
              "type": "linear"
            },
            "showPoints": "auto",
            "spanNulls": false,
            "stacking": {
              "group": "A",
              "mode": "none"
            },
            "thresholdsStyle": {
              "mode": "off"
            }
          },
          "mappings": [],
          "thresholds": {
            "mode": "absolute",
            "steps": [
              {
                "color": "green",
                "value": null
              },
              {
                "color": "red",
                "value": 80
              }
            ]
          }
        },
        "overrides": []
      },
      "gridPos": {
        "h": 8,
        "w": 12,
        "x": 0,
        "y": 8
      },
      "id": 3,
      "options": {
        "legend": {
          "calcs": [],
          "displayMode": "list",
          "placement": "bottom",
          "showLegend": true
        },
        "tooltip": {
          "mode": "single",
          "sort": "none"
        }
      },
      "pluginVersion": "11.3.1",
      "targets": [
        {
          "editorMode": "code",
          "expr": "rate(nodejs_gc_duration_seconds_sum{app=\"captcha-api\",kind=\"minor\"}[1m])",
          "format": "time_series",
          "legendFormat": "Minor",
          "range": true,
          "refId": "A"
        },
        {
          "datasource": {
            "type": "prometheus",
            "uid": "prometheus"
          },
          "editorMode": "code",
          "expr": "rate(nodejs_gc_duration_seconds_sum{app=\"captcha-api\",kind=\"incremental\"}[1m])",
          "format": "time_series",
          "hide": false,
          "instant": false,
          "legendFormat": "Incremental",
          "range": true,
          "refId": "B"
        },
        {
          "datasource": {
            "type": "prometheus",
            "uid": "prometheus"
          },
          "editorMode": "code",
          "expr": "rate(nodejs_gc_duration_seconds_sum{app=\"captcha-api\",kind=\"major\"}[1m])",
          "format": "time_series",
          "hide": false,
          "instant": false,
          "legendFormat": "Major",
          "range": true,
          "refId": "C"
        }
      ],
      "title": "Garbage Collection",
      "type": "timeseries"
    },
    {
      "datasource": {
        "type": "prometheus",
        "uid": "prometheus"
      },
      "fieldConfig": {
        "defaults": {
          "color": {
            "mode": "palette-classic"
          },
          "custom": {
            "axisBorderShow": false,
            "axisCenteredZero": false,
            "axisColorMode": "text",
            "axisLabel": "",
            "axisPlacement": "auto",
            "barAlignment": 0,
            "barWidthFactor": 0.6,
            "drawStyle": "line",
            "fillOpacity": 0,
            "gradientMode": "none",
            "hideFrom": {
              "legend": false,
              "tooltip": false,
              "viz": false
            },
            "insertNulls": false,
            "lineInterpolation": "linear",
            "lineWidth": 1,
            "pointSize": 5,
            "scaleDistribution": {
              "type": "linear"
            },
            "showPoints": "auto",
            "spanNulls": false,
            "stacking": {
              "group": "A",
              "mode": "none"
            },
            "thresholdsStyle": {
              "mode": "off"
            }
          },
          "mappings": [],
          "thresholds": {
            "mode": "absolute",
            "steps": [
              {
                "color": "green",
                "value": null
              },
              {
                "color": "red",
                "value": 80
              }
            ]
          },
          "unit": "s"
        },
        "overrides": [
          {
            "matcher": {
              "id": "byName",
              "options": "Value #A"
            },
            "properties": [
              {
                "id": "displayName",
                "value": "User CPU Time"
              }
            ]
          },
          {
            "matcher": {
              "id": "byName",
              "options": "Value #B"
            },
            "properties": [
              {
                "id": "displayName",
                "value": "System CPU Time"
              }
            ]
          },
          {
            "matcher": {
              "id": "byName",
              "options": "Value #C"
            },
            "properties": [
              {
                "id": "displayName",
                "value": "Total CPU Time"
              }
            ]
          }
        ]
      },
      "gridPos": {
        "h": 8,
        "w": 12,
        "x": 12,
        "y": 8
      },
      "id": 1,
      "options": {
        "legend": {
          "calcs": [],
          "displayMode": "list",
          "placement": "bottom",
          "showLegend": true
        },
        "tooltip": {
          "mode": "single",
          "sort": "none"
        }
      },
      "pluginVersion": "11.3.1",
      "targets": [
        {
          "datasource": {
            "type": "prometheus",
            "uid": "prometheus"
          },
          "editorMode": "code",
          "expr": "rate(process_cpu_user_seconds_total{app=\"captcha-api\"}[1m])",
          "format": "table",
          "legendFormat": "__auto",
          "range": true,
          "refId": "A"
        },
        {
          "datasource": {
            "type": "prometheus",
            "uid": "prometheus"
          },
          "editorMode": "code",
          "expr": "rate(process_cpu_system_seconds_total{app=\"captcha-api\"}[1m])",
          "format": "table",
          "hide": false,
          "instant": false,
          "legendFormat": "__auto",
          "range": true,
          "refId": "B"
        },
        {
          "datasource": {
            "type": "prometheus",
            "uid": "prometheus"
          },
          "editorMode": "code",
          "expr": "rate(process_cpu_seconds_total{app=\"captcha-api\"}[1m])",
          "format": "table",
          "hide": false,
          "instant": false,
          "legendFormat": "__auto",
          "range": true,
          "refId": "C"
        }
      ],
      "title": "CPU Utilization",
      "type": "timeseries"
    },
    {
      "datasource": {
        "type": "prometheus",
        "uid": "prometheus"
      },
      "fieldConfig": {
        "defaults": {
          "color": {
            "mode": "palette-classic"
          },
          "custom": {
            "hideFrom": {
              "legend": false,
              "tooltip": false,
              "viz": false
            }
          },
          "mappings": []
        },
        "overrides": [
          {
            "matcher": {
              "id": "byName",
              "options": "Value #A"
            },
            "properties": [
              {
                "id": "displayName",
                "value": "Waldo Found"
              }
            ]
          },
          {
            "matcher": {
              "id": "byName",
              "options": "Value #B"
            },
            "properties": [
              {
                "id": "displayName",
                "value": "Failed to find Waldo"
              }
            ]
          }
        ]
      },
      "gridPos": {
        "h": 8,
        "w": 12,
        "x": 0,
        "y": 16
      },
      "id": 7,
      "options": {
        "legend": {
          "displayMode": "list",
          "placement": "bottom",
          "showLegend": true
        },
        "pieType": "pie",
        "reduceOptions": {
          "calcs": [
            "lastNotNull"
          ],
          "fields": "",
          "values": false
        },
        "tooltip": {
          "mode": "single",
          "sort": "none"
        }
      },
      "pluginVersion": "11.3.1",
      "targets": [
        {
          "editorMode": "code",
          "expr": "charlie_successes{app=\"captcha-api\"}",
          "format": "table",
          "legendFormat": "Waldo Found",
          "range": true,
          "refId": "A"
        },
        {
          "datasource": {
            "type": "prometheus",
            "uid": "prometheus"
          },
          "editorMode": "code",
          "expr": "charlie_fails{app=\"captcha-api\"}",
          "format": "table",
          "hide": false,
          "instant": false,
          "legendFormat": "Failed to find Waldo",
          "range": true,
          "refId": "B"
        }
      ],
      "title": "Waldo Stats",
      "type": "piechart"
    },
    {
      "datasource": {
        "type": "loki",
        "uid": "P8E80F9AEF21F6940"
      },
      "fieldConfig": {
        "defaults": {},
        "overrides": []
      },
      "gridPos": {
        "h": 9,
        "w": 24,
        "x": 0,
        "y": 24
      },
      "id": 5,
      "options": {
        "dedupStrategy": "none",
        "enableLogDetails": true,
        "prettifyLogMessage": false,
        "showCommonLabels": false,
        "showLabels": false,
        "showTime": false,
        "sortOrder": "Descending",
        "wrapLogMessage": false
      },
      "pluginVersion": "11.3.1",
      "targets": [
        {
          "datasource": {
            "type": "loki",
            "uid": "P8E80F9AEF21F6940"
          },
          "editorMode": "builder",
          "expr": "{app=\"captcha-api\"} |= ``",
          "queryType": "range",
          "refId": "A"
        }
      ],
      "title": "API Logs",
      "type": "logs"
    },
    {
      "datasource": {
        "type": "loki",
        "uid": "P8E80F9AEF21F6940"
      },
      "fieldConfig": {
        "defaults": {},
        "overrides": []
      },
      "gridPos": {
        "h": 7,
        "w": 24,
        "x": 0,
        "y": 33
      },
      "id": 6,
      "options": {
        "dedupStrategy": "none",
        "enableLogDetails": true,
        "prettifyLogMessage": false,
        "showCommonLabels": false,
        "showLabels": false,
        "showTime": false,
        "sortOrder": "Descending",
        "wrapLogMessage": false
      },
      "pluginVersion": "11.3.1",
      "targets": [
        {
          "datasource": {
            "type": "loki",
            "uid": "P8E80F9AEF21F6940"
          },
          "editorMode": "builder",
          "expr": "{app=\"frontend\"} |= ``",
          "queryType": "range",
          "refId": "A"
        }
      ],
      "title": "Frontend Logs",
      "type": "logs"
    }
  ],
  "preload": false,
  "schemaVersion": 40,
  "tags": [],
  "templating": {
    "list": []
  },
  "time": {
    "from": "now-15m",
    "to": "now"
  },
  "timepicker": {},
  "timezone": "browser",
  "title": "NDI TTY",
  "uid": "ae61uvigu2n7kb",
  "version": 13,
  "weekStart": ""
}